irr_nonauth_cleanup
